dotenv_run.py
python_dotenv_run-0.1.4.dist-info/DESCRIPTION.rst
python_dotenv_run-0.1.4.dist-info/METADATA
python_dotenv_run-0.1.4.dist-info/RECORD
python_dotenv_run-0.1.4.dist-info/WHEEL
python_dotenv_run-0.1.4.dist-info/entry_points.txt
python_dotenv_run-0.1.4.dist-info/metadata.json
python_dotenv_run-0.1.4.dist-info/top_level.txt
